hema/__init__.py
hema/models/__init__.py
hema/models/utils.py
hema/models/DinoSR/EMA.py
hema/models/DinoSR/__init__.py
hema/models/DinoSR/model.py
hema/models/conformer/__init__.py
hema/models/conformer/activation.py
hema/models/conformer/attention.py
hema/models/conformer/basic.py
hema/models/conformer/conformer.py
hema/models/conformer/convolution.py
hema/models/conformer/embedding.py
hema/models/conformer/encoder.py
hema/models/conformer/feedforward.py
hema/models/conformer/model.py
hema/models/conformer_dp/__init__.py
hema/models/conformer_dp/activation.py
hema/models/conformer_dp/attention.py
hema/models/conformer_dp/basic.py
hema/models/conformer_dp/conformer.py
hema/models/conformer_dp/convolution.py
hema/models/conformer_dp/embedding.py
hema/models/conformer_dp/encoder.py
hema/models/conformer_dp/feedforward.py
hema/models/conformer_dp/model.py
hema/nn/__init__.py
hema/nn/conv_blocks.py
hema/nn/conv_feature_extractor.py
hema/visualization/__init__.py
hema/visualization/psd.py
src/__init__.py
src/models/__init__.py
src/models/utils.py
src/models/DinoSR/EMA.py
src/models/DinoSR/__init__.py
src/models/DinoSR/model.py
src/models/conformer/__init__.py
src/models/conformer/model.py
src/models/conformer_dp/__init__.py
src/models/conformer_dp/activation.py
src/models/conformer_dp/attention.py
src/models/conformer_dp/basic.py
src/models/conformer_dp/conformer.py
src/models/conformer_dp/convolution.py
src/models/conformer_dp/embedding.py
src/models/conformer_dp/encoder.py
src/models/conformer_dp/feedforward.py
src/models/conformer_dp/model.py
src/nn/__init__.py
src/nn/conv_blocks.py
src/nn/conv_feature_extractor.py
src/visualization/__init__.py
src/visualization/psd.py
test/__init__.py
test/dinosr_test.py
hema-0.1.4.dist-info/METADATA
hema-0.1.4.dist-info/WHEEL
hema-0.1.4.dist-info/top_level.txt
hema-0.1.4.dist-info/RECORD
